geoffrey_radon-0.0.3.dist-info/DESCRIPTION.rst
geoffrey_radon-0.0.3.dist-info/RECORD
geoffrey_radon-0.0.3.dist-info/WHEEL
geoffrey_radon-0.0.3.dist-info/top_level.txt
geoffrey_radon-0.0.3.dist-info/metadata.json
geoffrey_radon-0.0.3.dist-info/METADATA
geoffreyplugins/__init__.py
geoffreyplugins/radon.py
geoffreyplugins/radon/main.js
geoffreyplugins/radon/assets/panel.html
geoffreyplugins/radon/assets/.gitkeep
