Metadata-Version: 2.0
Name: geoffrey-radon
Version: 0.0.3
Summary: a Python tool that computes various metrics from the source code
Home-page: https://github.com/GeoffreyCI/geoffrey-radon
Author: Miguel Reguero Bejar
Author-email: mreguerob0@gmail.com
License: UNKNOWN
Platform: UNKNOWN
